viterbi_trellis/.DS_Store
viterbi_trellis/__init__.py
viterbi_trellis/utils.py
viterbi_trellis/viterbi.py
viterbi_trellis/viterbi_exceptions.py
viterbi_trellis/viterbi_test.py
viterbi_trellis-0.0.3.dist-info/DESCRIPTION.rst
viterbi_trellis-0.0.3.dist-info/METADATA
viterbi_trellis-0.0.3.dist-info/RECORD
viterbi_trellis-0.0.3.dist-info/WHEEL
viterbi_trellis-0.0.3.dist-info/metadata.json
viterbi_trellis-0.0.3.dist-info/top_level.txt
