Metadata-Version: 2.0
Name: viterbi-trellis
Version: 0.0.3
Summary: Library to compute the best path through a trellis graph using the Viterbi algorithm.
Home-page: https://github.com/eraoul/viterbi_trellis
Author: Eric P. Nichols
Author-email: epnichols@gmail.com
License: UNKNOWN
Keywords: viterbi trellis best_path
Platform: UNKNOWN
Classifier: Development Status :: 3 - Alpha
Classifier: Intended Audience :: Developers
Classifier: License :: OSI Approved :: MIT License
Classifier: Programming Language :: Python :: 2
Classifier: Programming Language :: Python :: 2.7
Classifier: Programming Language :: Python :: 3
Classifier: Programming Language :: Python :: 3.4
Classifier: Programming Language :: Python :: 3.5
Classifier: Programming Language :: Python :: 3.6
Provides-Extra: dev
Requires-Dist: check-manifest; extra == 'dev'
Provides-Extra: test
Requires-Dist: coverage; extra == 'test'
